{"name":"Nebulaic_Toaster","tagline":"A game of Lies, Decisions and Space","body":"![Icon](https://raw.githubusercontent.com/chromebookbob/Nebulaic-Toaster-Kivy/master/data/icon.png)\r\n### Welcome to Nebulaic_Toaster.\r\nA game in development.\r\n\r\nNebulaic_Toaster is the second iteration of the text based game of the same name (see: https://github.com/chromebookbob/nebulaic-toaster). It is written in kivy and I will be releasing it on as many platforms as possible.\r\n\r\n### Authors and Contributors\r\nchromebookbob\r\n\r\n","google":"UA-43154030-2","note":"Don't delete this file! It's used internally to help with page regeneration."}